[
    {
        "timestamp": "2025-02-23 00:22:31",
        "depth": 10,
        "pressure": 2.0,
        "oxygen_toxicity": 0.42,
        "ndl": 56.67,
        "rgbm_factor": 0.91992,
        "total_time": 13.58,
        "time_at_depth": 1
    },
    {
        "timestamp": "2025-02-23 00:23:27",
        "depth": 20,
        "pressure": 3.0,
        "oxygen_toxicity": 0.63,
        "ndl": 53.33,
        "rgbm_factor": 0.83238,
        "total_time": 69.1,
        "time_at_depth": 1
    },
    {
        "timestamp": "2025-02-23 00:23:27",
        "depth": 30,
        "pressure": 4.0,
        "oxygen_toxicity": 0.84,
        "ndl": 50.0,
        "rgbm_factor": 0.75317,
        "total_time": 69.33,
        "time_at_depth": 1
    },
    {
        "timestamp": "2025-02-23 00:23:27",
        "depth": 40,
        "pressure": 5.0,
        "oxygen_toxicity": 1.05,
        "ndl": 46.67,
        "rgbm_factor": 0.68149,
        "total_time": 69.57,
        "time_at_depth": 1
    },
    {
        "timestamp": "2025-02-23 00:23:27",
        "depth": 50,
        "pressure": 6.0,
        "oxygen_toxicity": 1.26,
        "ndl": 43.33,
        "rgbm_factor": 0.61664,
        "total_time": 69.81,
        "time_at_depth": 1
    },
    {
        "timestamp": "2025-02-23 00:23:27",
        "depth": 60,
        "pressure": 7.0,
        "oxygen_toxicity": 1.47,
        "ndl": 40.0,
        "rgbm_factor": 0.55796,
        "total_time": 70.05,
        "time_at_depth": 1
    },
    {
        "timestamp": "2025-02-23 00:23:28",
        "depth": 70,
        "pressure": 8.0,
        "oxygen_toxicity": 1.68,
        "ndl": 36.67,
        "rgbm_factor": 0.50486,
        "total_time": 70.3,
        "time_at_depth": 1
    },
    {
        "timestamp": "2025-02-23 00:23:28",
        "depth": 80,
        "pressure": 9.0,
        "oxygen_toxicity": 1.89,
        "ndl": 33.33,
        "rgbm_factor": 0.45682,
        "total_time": 70.57,
        "time_at_depth": 1
    },
    {
        "timestamp": "2025-02-23 00:23:28",
        "depth": 90,
        "pressure": 10.0,
        "oxygen_toxicity": 2.1,
        "ndl": 30.0,
        "rgbm_factor": 0.41335,
        "total_time": 70.86,
        "time_at_depth": 1
    },
    {
        "timestamp": "2025-02-23 00:23:29",
        "depth": 100,
        "pressure": 11.0,
        "oxygen_toxicity": 2.31,
        "ndl": 26.67,
        "rgbm_factor": 0.37401,
        "total_time": 71.13,
        "time_at_depth": 1
    },
    {
        "timestamp": "2025-02-23 00:23:29",
        "depth": 110,
        "pressure": 12.0,
        "oxygen_toxicity": 2.52,
        "ndl": 23.33,
        "rgbm_factor": 0.33842,
        "total_time": 71.37,
        "time_at_depth": 1
    },
    {
        "timestamp": "2025-02-23 00:23:29",
        "depth": 120,
        "pressure": 13.0,
        "oxygen_toxicity": 2.73,
        "ndl": 20.0,
        "rgbm_factor": 0.30621,
        "total_time": 71.63,
        "time_at_depth": 1
    },
    {
        "timestamp": "2025-02-23 00:23:40",
        "depth": 130,
        "pressure": 14.0,
        "oxygen_toxicity": 2.94,
        "ndl": 16.67,
        "rgbm_factor": 0.27707,
        "total_time": 82.65,
        "time_at_depth": 1
    },
    {
        "timestamp": "2025-02-23 00:23:40",
        "depth": 140,
        "pressure": 15.0,
        "oxygen_toxicity": 3.15,
        "ndl": 13.33,
        "rgbm_factor": 0.25071,
        "total_time": 82.93,
        "time_at_depth": 1
    },
    {
        "timestamp": "2025-02-23 00:23:41",
        "depth": 150,
        "pressure": 16.0,
        "oxygen_toxicity": 3.36,
        "ndl": 10.0,
        "rgbm_factor": 0.22685,
        "total_time": 83.16,
        "time_at_depth": 1
    },
    {
        "timestamp": "2025-02-23 00:23:41",
        "depth": 160,
        "pressure": 17.0,
        "oxygen_toxicity": 3.57,
        "ndl": 6.67,
        "rgbm_factor": 0.20526,
        "total_time": 83.35,
        "time_at_depth": 1
    },
    {
        "timestamp": "2025-02-23 00:23:41",
        "depth": 170,
        "pressure": 18.0,
        "oxygen_toxicity": 3.78,
        "ndl": 3.33,
        "rgbm_factor": 0.18573,
        "total_time": 83.55,
        "time_at_depth": 1
    },
    {
        "timestamp": "2025-02-23 00:23:41",
        "depth": 180,
        "pressure": 19.0,
        "oxygen_toxicity": 3.99,
        "ndl": 0.0,
        "rgbm_factor": 0.16805,
        "total_time": 83.74,
        "time_at_depth": 1
    },
    {
        "timestamp": "2025-02-23 00:23:41",
        "depth": 190,
        "pressure": 20.0,
        "oxygen_toxicity": 4.2,
        "ndl": -3.33,
        "rgbm_factor": 0.15206,
        "total_time": 83.95,
        "time_at_depth": 1
    },
    {
        "timestamp": "2025-02-23 00:23:42",
        "depth": 200,
        "pressure": 21.0,
        "oxygen_toxicity": 4.41,
        "ndl": -6.67,
        "rgbm_factor": 0.13759,
        "total_time": 84.16,
        "time_at_depth": 1
    },
    {
        "timestamp": "2025-02-23 00:23:46",
        "depth": 190,
        "pressure": 20.0,
        "oxygen_toxicity": 4.2,
        "ndl": 0.39,
        "rgbm_factor": 0.15,
        "total_time": 88.73,
        "time_at_depth": 1
    },
    {
        "timestamp": "2025-02-23 00:29:21",
        "depth": 180,
        "pressure": 19.0,
        "oxygen_toxicity": 3.99,
        "ndl": 0.43,
        "rgbm_factor": 0.17,
        "total_time": 423.77,
        "time_at_depth": 1
    },
    {
        "timestamp": "2025-02-23 00:29:23",
        "depth": 190,
        "pressure": 20.0,
        "oxygen_toxicity": 4.2,
        "ndl": -3.33,
        "rgbm_factor": 0.98528,
        "total_time": 425.17,
        "time_at_depth": 335.25
    },
    {
        "timestamp": "2025-02-23 00:29:23",
        "depth": 200,
        "pressure": 21.0,
        "oxygen_toxicity": 4.41,
        "ndl": -6.67,
        "rgbm_factor": 0.14566,
        "total_time": 425.41,
        "time_at_depth": 4.58
    },
    {
        "timestamp": "2025-02-23 00:29:23",
        "depth": 210,
        "pressure": 22.0,
        "oxygen_toxicity": 4.62,
        "ndl": -10.0,
        "rgbm_factor": 0.1245,
        "total_time": 425.62,
        "time_at_depth": 1
    },
    {
        "timestamp": "2025-02-23 00:29:23",
        "depth": 220,
        "pressure": 23.0,
        "oxygen_toxicity": 4.83,
        "ndl": -13.33,
        "rgbm_factor": 0.11265,
        "total_time": 425.82,
        "time_at_depth": 1
    },
    {
        "timestamp": "2025-02-23 00:29:23",
        "depth": 230,
        "pressure": 24.0,
        "oxygen_toxicity": 5.04,
        "ndl": -16.67,
        "rgbm_factor": 0.10193,
        "total_time": 426.06,
        "time_at_depth": 1
    }
]